eddington/__init__.py
eddington/__main__.py
eddington/consts.py
eddington/exceptions.py
eddington/fitting.py
eddington/fitting_data.py
eddington/fitting_function_class.py
eddington/fitting_functions_list.py
eddington/fitting_functions_registry.py
eddington/fitting_result.py
eddington/io_util.py
eddington/plot.py
eddington/print_util.py
eddington/random_util.py
eddington/statistics.py
eddington/cli/__init__.py
eddington/cli/common_flags.py
eddington/cli/fit.py
eddington/cli/fit_random.py
eddington/cli/list.py
eddington/cli/main_cli.py
eddington/cli/statistics_cli.py
eddington/cli/util.py
eddington-0.0.23.dist-info/LICENSE
eddington-0.0.23.dist-info/METADATA
eddington-0.0.23.dist-info/WHEEL
eddington-0.0.23.dist-info/entry_points.txt
eddington-0.0.23.dist-info/top_level.txt
eddington-0.0.23.dist-info/RECORD
