Metadata-Version: 2.1
Name: eddington
Version: 0.0.23
Summary: Open source, easy to use, data fitting platform.
Home-page: https://github.com/EddLabs/eddington
Author: Sagi Shadur
Author-email: saroad2@gmail.com
Maintainer: Sagi Shadur
Maintainer-email: saroad2@gmail.com
License: Apache License
Keywords: laboratory,fitting,data
Platform: any
Classifier: Development Status :: 3 - Alpha
Classifier: Intended Audience :: Developers
Classifier: License :: OSI Approved :: BSD License
Classifier: Operating System :: OS Independent
Classifier: Programming Language :: Python :: 3
Classifier: Programming Language :: Python :: 3.6
Classifier: Programming Language :: Python :: 3.7
Classifier: Programming Language :: Python :: 3.8
Classifier: Programming Language :: Python :: 3 :: Only
Classifier: Topic :: Software Development
Classifier: Topic :: Utilities
Requires-Python: >=3.6
Requires-Dist: click (>=7.1.2)
Requires-Dist: prettytable (>=2.0.0)
Requires-Dist: scipy (>=1.5.4)
Requires-Dist: numpy (==1.19.3)
Requires-Dist: openpyxl (>=3.0.5)
Requires-Dist: matplotlib (>=3.3.3)
Requires-Dist: dataclasses (>=0.7) ; python_version == "3.6"
